pyodide_importer/__init__.py
pyodide_importer/api.py
pyodide_importer/import_hook.py
pyodide_importer/tests/__init__.py
pyodide_importer/tests/test_import_hook.py
pyodide_importer-0.0.2.dist-info/LICENSE
pyodide_importer-0.0.2.dist-info/METADATA
pyodide_importer-0.0.2.dist-info/WHEEL
pyodide_importer-0.0.2.dist-info/top_level.txt
pyodide_importer-0.0.2.dist-info/RECORD
